{
    "nodes": {
        "6859": {
            "AIRLINE_CODE": "MU3656",
            "FLIGHT_ID": 6859,
            "DEPARTURE_AIRPORT": "上海虹桥国际机场",
            "ARRIVAL_AIRPORT": "广州新白云国际机场",
            "TIME_DEPARTURE": "1:18:45",
            "TIME_ARRIVAL": "1:21:05",
            "CITY_DEPARTURE": "上海",
            "CITY_ARRIVAL": "广州",
            "MODE": "77B"
        },
        "6860": {
            "AIRLINE_CODE": "MU3656",
            "FLIGHT_ID": 6860,
            "DEPARTURE_AIRPORT": "上海虹桥国际机场",
            "ARRIVAL_AIRPORT": "广州新白云国际机场",
            "TIME_DEPARTURE": "2:18:45",
            "TIME_ARRIVAL": "2:21:05",
            "CITY_DEPARTURE": "上海",
            "CITY_ARRIVAL": "广州",
            "MODE": "77B"
        },
        "6861": {
            "AIRLINE_CODE": "MU3656",
            "FLIGHT_ID": 6861,
            "DEPARTURE_AIRPORT": "上海虹桥国际机场",
            "ARRIVAL_AIRPORT": "广州新白云国际机场",
            "TIME_DEPARTURE": "3:18:45",
            "TIME_ARRIVAL": "3:21:05",
            "CITY_DEPARTURE": "上海",
            "CITY_ARRIVAL": "广州",
            "MODE": "77B"
        },
        "6862": {
            "AIRLINE_CODE": "MU3656",
            "FLIGHT_ID": 6862,
            "DEPARTURE_AIRPORT": "上海虹桥国际机场",
            "ARRIVAL_AIRPORT": "广州新白云国际机场",
            "TIME_DEPARTURE": "4:18:45",
            "TIME_ARRIVAL": "4:21:05",
            "CITY_DEPARTURE": "上海",
            "CITY_ARRIVAL": "广州",
            "MODE": "77B"
        },
        "6863": {
            "AIRLINE_CODE": "MU3656",
            "FLIGHT_ID": 6863,
            "DEPARTURE_AIRPORT": "上海虹桥国际机场",
            "ARRIVAL_AIRPORT": "广州新白云国际机场",
            "TIME_DEPARTURE": "5:18:45",
            "TIME_ARRIVAL": "5:21:05",
            "CITY_DEPARTURE": "上海",
            "CITY_ARRIVAL": "广州",
            "MODE": "77B"
        },
        "6864": {
            "AIRLINE_CODE": "MU3656",
            "FLIGHT_ID": 6864,
            "DEPARTURE_AIRPORT": "上海虹桥国际机场",
            "ARRIVAL_AIRPORT": "广州新白云国际机场",
            "TIME_DEPARTURE": "6:18:45",
            "TIME_ARRIVAL": "6:21:05",
            "CITY_DEPARTURE": "上海",
            "CITY_ARRIVAL": "广州",
            "MODE": "77B"
        },
        "6865": {
            "AIRLINE_CODE": "MU3656",
            "FLIGHT_ID": 6865,
            "DEPARTURE_AIRPORT": "上海虹桥国际机场",
            "ARRIVAL_AIRPORT": "广州新白云国际机场",
            "TIME_DEPARTURE": "7:18:45",
            "TIME_ARRIVAL": "7:21:05",
            "CITY_DEPARTURE": "上海",
            "CITY_ARRIVAL": "广州",
            "MODE": "77B"
        },
        "6866": {
            "AIRLINE_CODE": "CZ3572",
            "FLIGHT_ID": 6866,
            "DEPARTURE_AIRPORT": "上海虹桥国际机场",
            "ARRIVAL_AIRPORT": "广州新白云国际机场",
            "TIME_DEPARTURE": "1:18:45",
            "TIME_ARRIVAL": "1:21:05",
            "CITY_DEPARTURE": "上海",
            "CITY_ARRIVAL": "广州",
            "MODE": "77B"
        },
        "6867": {
            "AIRLINE_CODE": "CZ3572",
            "FLIGHT_ID": 6867,
            "DEPARTURE_AIRPORT": "上海虹桥国际机场",
            "ARRIVAL_AIRPORT": "广州新白云国际机场",
            "TIME_DEPARTURE": "2:18:45",
            "TIME_ARRIVAL": "2:21:05",
            "CITY_DEPARTURE": "上海",
            "CITY_ARRIVAL": "广州",
            "MODE": "77B"
        },
        "6868": {
            "AIRLINE_CODE": "CZ3572",
            "FLIGHT_ID": 6868,
            "DEPARTURE_AIRPORT": "上海虹桥国际机场",
            "ARRIVAL_AIRPORT": "广州新白云国际机场",
            "TIME_DEPARTURE": "3:18:45",
            "TIME_ARRIVAL": "3:21:05",
            "CITY_DEPARTURE": "上海",
            "CITY_ARRIVAL": "广州",
            "MODE": "77B"
        },
        "6869": {
            "AIRLINE_CODE": "CZ3572",
            "FLIGHT_ID": 6869,
            "DEPARTURE_AIRPORT": "上海虹桥国际机场",
            "ARRIVAL_AIRPORT": "广州新白云国际机场",
            "TIME_DEPARTURE": "4:18:45",
            "TIME_ARRIVAL": "4:21:05",
            "CITY_DEPARTURE": "上海",
            "CITY_ARRIVAL": "广州",
            "MODE": "77B"
        },
        "6870": {
            "AIRLINE_CODE": "CZ3572",
            "FLIGHT_ID": 6870,
            "DEPARTURE_AIRPORT": "上海虹桥国际机场",
            "ARRIVAL_AIRPORT": "广州新白云国际机场",
            "TIME_DEPARTURE": "5:18:45",
            "TIME_ARRIVAL": "5:21:05",
            "CITY_DEPARTURE": "上海",
            "CITY_ARRIVAL": "广州",
            "MODE": "77B"
        },
        "6871": {
            "AIRLINE_CODE": "CZ3572",
            "FLIGHT_ID": 6871,
            "DEPARTURE_AIRPORT": "上海虹桥国际机场",
            "ARRIVAL_AIRPORT": "广州新白云国际机场",
            "TIME_DEPARTURE": "6:18:45",
            "TIME_ARRIVAL": "6:21:05",
            "CITY_DEPARTURE": "上海",
            "CITY_ARRIVAL": "广州",
            "MODE": "77B"
        },
        "6872": {
            "AIRLINE_CODE": "CZ3572",
            "FLIGHT_ID": 6872,
            "DEPARTURE_AIRPORT": "上海虹桥国际机场",
            "ARRIVAL_AIRPORT": "广州新白云国际机场",
            "TIME_DEPARTURE": "7:18:45",
            "TIME_ARRIVAL": "7:21:05",
            "CITY_DEPARTURE": "上海",
            "CITY_ARRIVAL": "广州",
            "MODE": "77B"
        },
        "6873": {
            "AIRLINE_CODE": "MF1456",
            "FLIGHT_ID": 6873,
            "DEPARTURE_AIRPORT": "上海虹桥国际机场",
            "ARRIVAL_AIRPORT": "广州新白云国际机场",
            "TIME_DEPARTURE": "1:18:45",
            "TIME_ARRIVAL": "1:21:05",
            "CITY_DEPARTURE": "上海",
            "CITY_ARRIVAL": "广州",
            "MODE": "77B"
        },
        "6874": {
            "AIRLINE_CODE": "MF1456",
            "FLIGHT_ID": 6874,
            "DEPARTURE_AIRPORT": "上海虹桥国际机场",
            "ARRIVAL_AIRPORT": "广州新白云国际机场",
            "TIME_DEPARTURE": "2:18:45",
            "TIME_ARRIVAL": "2:21:05",
            "CITY_DEPARTURE": "上海",
            "CITY_ARRIVAL": "广州",
            "MODE": "77B"
        },
        "6875": {
            "AIRLINE_CODE": "MF1456",
            "FLIGHT_ID": 6875,
            "DEPARTURE_AIRPORT": "上海虹桥国际机场",
            "ARRIVAL_AIRPORT": "广州新白云国际机场",
            "TIME_DEPARTURE": "3:18:45",
            "TIME_ARRIVAL": "3:21:05",
            "CITY_DEPARTURE": "上海",
            "CITY_ARRIVAL": "广州",
            "MODE": "77B"
        },
        "6876": {
            "AIRLINE_CODE": "MF1456",
            "FLIGHT_ID": 6876,
            "DEPARTURE_AIRPORT": "上海虹桥国际机场",
            "ARRIVAL_AIRPORT": "广州新白云国际机场",
            "TIME_DEPARTURE": "4:18:45",
            "TIME_ARRIVAL": "4:21:05",
            "CITY_DEPARTURE": "上海",
            "CITY_ARRIVAL": "广州",
            "MODE": "77B"
        },
        "6877": {
            "AIRLINE_CODE": "MF1456",
            "FLIGHT_ID": 6877,
            "DEPARTURE_AIRPORT": "上海虹桥国际机场",
            "ARRIVAL_AIRPORT": "广州新白云国际机场",
            "TIME_DEPARTURE": "5:18:45",
            "TIME_ARRIVAL": "5:21:05",
            "CITY_DEPARTURE": "上海",
            "CITY_ARRIVAL": "广州",
            "MODE": "77B"
        },
        "6878": {
            "AIRLINE_CODE": "MF1456",
            "FLIGHT_ID": 6878,
            "DEPARTURE_AIRPORT": "上海虹桥国际机场",
            "ARRIVAL_AIRPORT": "广州新白云国际机场",
            "TIME_DEPARTURE": "6:18:45",
            "TIME_ARRIVAL": "6:21:05",
            "CITY_DEPARTURE": "上海",
            "CITY_ARRIVAL": "广州",
            "MODE": "77B"
        },
        "6879": {
            "AIRLINE_CODE": "MF1456",
            "FLIGHT_ID": 6879,
            "DEPARTURE_AIRPORT": "上海虹桥国际机场",
            "ARRIVAL_AIRPORT": "广州新白云国际机场",
            "TIME_DEPARTURE": "7:18:45",
            "TIME_ARRIVAL": "7:21:05",
            "CITY_DEPARTURE": "上海",
            "CITY_ARRIVAL": "广州",
            "MODE": "77B"
        },
        "41183": {
            "AIRLINE_CODE": "MU3657",
            "FLIGHT_ID": 41183,
            "DEPARTURE_AIRPORT": "广州新白云国际机场",
            "ARRIVAL_AIRPORT": "上海虹桥国际机场",
            "TIME_DEPARTURE": "1:15:05",
            "TIME_ARRIVAL": "1:17:20",
            "CITY_DEPARTURE": "广州",
            "CITY_ARRIVAL": "上海",
            "MODE": "77B"
        },
        "41184": {
            "AIRLINE_CODE": "MU3657",
            "FLIGHT_ID": 41184,
            "DEPARTURE_AIRPORT": "广州新白云国际机场",
            "ARRIVAL_AIRPORT": "上海虹桥国际机场",
            "TIME_DEPARTURE": "2:15:05",
            "TIME_ARRIVAL": "2:17:20",
            "CITY_DEPARTURE": "广州",
            "CITY_ARRIVAL": "上海",
            "MODE": "77B"
        },
        "41185": {
            "AIRLINE_CODE": "MU3657",
            "FLIGHT_ID": 41185,
            "DEPARTURE_AIRPORT": "广州新白云国际机场",
            "ARRIVAL_AIRPORT": "上海虹桥国际机场",
            "TIME_DEPARTURE": "3:15:05",
            "TIME_ARRIVAL": "3:17:20",
            "CITY_DEPARTURE": "广州",
            "CITY_ARRIVAL": "上海",
            "MODE": "77B"
        },
        "41186": {
            "AIRLINE_CODE": "MU3657",
            "FLIGHT_ID": 41186,
            "DEPARTURE_AIRPORT": "广州新白云国际机场",
            "ARRIVAL_AIRPORT": "上海虹桥国际机场",
            "TIME_DEPARTURE": "4:15:05",
            "TIME_ARRIVAL": "4:17:20",
            "CITY_DEPARTURE": "广州",
            "CITY_ARRIVAL": "上海",
            "MODE": "77B"
        },
        "41187": {
            "AIRLINE_CODE": "MU3657",
            "FLIGHT_ID": 41187,
            "DEPARTURE_AIRPORT": "广州新白云国际机场",
            "ARRIVAL_AIRPORT": "上海虹桥国际机场",
            "TIME_DEPARTURE": "5:15:05",
            "TIME_ARRIVAL": "5:17:20",
            "CITY_DEPARTURE": "广州",
            "CITY_ARRIVAL": "上海",
            "MODE": "77B"
        },
        "41188": {
            "AIRLINE_CODE": "MU3657",
            "FLIGHT_ID": 41188,
            "DEPARTURE_AIRPORT": "广州新白云国际机场",
            "ARRIVAL_AIRPORT": "上海虹桥国际机场",
            "TIME_DEPARTURE": "6:15:05",
            "TIME_ARRIVAL": "6:17:20",
            "CITY_DEPARTURE": "广州",
            "CITY_ARRIVAL": "上海",
            "MODE": "77B"
        },
        "41189": {
            "AIRLINE_CODE": "MU3657",
            "FLIGHT_ID": 41189,
            "DEPARTURE_AIRPORT": "广州新白云国际机场",
            "ARRIVAL_AIRPORT": "上海虹桥国际机场",
            "TIME_DEPARTURE": "7:15:05",
            "TIME_ARRIVAL": "7:17:20",
            "CITY_DEPARTURE": "广州",
            "CITY_ARRIVAL": "上海",
            "MODE": "77B"
        },
        "41190": {
            "AIRLINE_CODE": "CZ3571",
            "FLIGHT_ID": 41190,
            "DEPARTURE_AIRPORT": "广州新白云国际机场",
            "ARRIVAL_AIRPORT": "上海虹桥国际机场",
            "TIME_DEPARTURE": "1:15:05",
            "TIME_ARRIVAL": "1:17:20",
            "CITY_DEPARTURE": "广州",
            "CITY_ARRIVAL": "上海",
            "MODE": "77B"
        },
        "41191": {
            "AIRLINE_CODE": "CZ3571",
            "FLIGHT_ID": 41191,
            "DEPARTURE_AIRPORT": "广州新白云国际机场",
            "ARRIVAL_AIRPORT": "上海虹桥国际机场",
            "TIME_DEPARTURE": "2:15:05",
            "TIME_ARRIVAL": "2:17:20",
            "CITY_DEPARTURE": "广州",
            "CITY_ARRIVAL": "上海",
            "MODE": "77B"
        },
        "41192": {
            "AIRLINE_CODE": "CZ3571",
            "FLIGHT_ID": 41192,
            "DEPARTURE_AIRPORT": "广州新白云国际机场",
            "ARRIVAL_AIRPORT": "上海虹桥国际机场",
            "TIME_DEPARTURE": "3:15:05",
            "TIME_ARRIVAL": "3:17:20",
            "CITY_DEPARTURE": "广州",
            "CITY_ARRIVAL": "上海",
            "MODE": "77B"
        },
        "41193": {
            "AIRLINE_CODE": "CZ3571",
            "FLIGHT_ID": 41193,
            "DEPARTURE_AIRPORT": "广州新白云国际机场",
            "ARRIVAL_AIRPORT": "上海虹桥国际机场",
            "TIME_DEPARTURE": "4:15:05",
            "TIME_ARRIVAL": "4:17:20",
            "CITY_DEPARTURE": "广州",
            "CITY_ARRIVAL": "上海",
            "MODE": "77B"
        },
        "41194": {
            "AIRLINE_CODE": "CZ3571",
            "FLIGHT_ID": 41194,
            "DEPARTURE_AIRPORT": "广州新白云国际机场",
            "ARRIVAL_AIRPORT": "上海虹桥国际机场",
            "TIME_DEPARTURE": "5:15:05",
            "TIME_ARRIVAL": "5:17:20",
            "CITY_DEPARTURE": "广州",
            "CITY_ARRIVAL": "上海",
            "MODE": "77B"
        },
        "41195": {
            "AIRLINE_CODE": "CZ3571",
            "FLIGHT_ID": 41195,
            "DEPARTURE_AIRPORT": "广州新白云国际机场",
            "ARRIVAL_AIRPORT": "上海虹桥国际机场",
            "TIME_DEPARTURE": "6:15:05",
            "TIME_ARRIVAL": "6:17:20",
            "CITY_DEPARTURE": "广州",
            "CITY_ARRIVAL": "上海",
            "MODE": "77B"
        },
        "41196": {
            "AIRLINE_CODE": "CZ3571",
            "FLIGHT_ID": 41196,
            "DEPARTURE_AIRPORT": "广州新白云国际机场",
            "ARRIVAL_AIRPORT": "上海虹桥国际机场",
            "TIME_DEPARTURE": "7:15:05",
            "TIME_ARRIVAL": "7:17:20",
            "CITY_DEPARTURE": "广州",
            "CITY_ARRIVAL": "上海",
            "MODE": "77B"
        },
        "41197": {
            "AIRLINE_CODE": "MF1455",
            "FLIGHT_ID": 41197,
            "DEPARTURE_AIRPORT": "广州新白云国际机场",
            "ARRIVAL_AIRPORT": "上海虹桥国际机场",
            "TIME_DEPARTURE": "1:15:05",
            "TIME_ARRIVAL": "1:17:20",
            "CITY_DEPARTURE": "广州",
            "CITY_ARRIVAL": "上海",
            "MODE": "77B"
        },
        "41198": {
            "AIRLINE_CODE": "MF1455",
            "FLIGHT_ID": 41198,
            "DEPARTURE_AIRPORT": "广州新白云国际机场",
            "ARRIVAL_AIRPORT": "上海虹桥国际机场",
            "TIME_DEPARTURE": "2:15:05",
            "TIME_ARRIVAL": "2:17:20",
            "CITY_DEPARTURE": "广州",
            "CITY_ARRIVAL": "上海",
            "MODE": "77B"
        },
        "41199": {
            "AIRLINE_CODE": "MF1455",
            "FLIGHT_ID": 41199,
            "DEPARTURE_AIRPORT": "广州新白云国际机场",
            "ARRIVAL_AIRPORT": "上海虹桥国际机场",
            "TIME_DEPARTURE": "3:15:05",
            "TIME_ARRIVAL": "3:17:20",
            "CITY_DEPARTURE": "广州",
            "CITY_ARRIVAL": "上海",
            "MODE": "77B"
        },
        "41200": {
            "AIRLINE_CODE": "MF1455",
            "FLIGHT_ID": 41200,
            "DEPARTURE_AIRPORT": "广州新白云国际机场",
            "ARRIVAL_AIRPORT": "上海虹桥国际机场",
            "TIME_DEPARTURE": "4:15:05",
            "TIME_ARRIVAL": "4:17:20",
            "CITY_DEPARTURE": "广州",
            "CITY_ARRIVAL": "上海",
            "MODE": "77B"
        },
        "41201": {
            "AIRLINE_CODE": "MF1455",
            "FLIGHT_ID": 41201,
            "DEPARTURE_AIRPORT": "广州新白云国际机场",
            "ARRIVAL_AIRPORT": "上海虹桥国际机场",
            "TIME_DEPARTURE": "5:15:05",
            "TIME_ARRIVAL": "5:17:20",
            "CITY_DEPARTURE": "广州",
            "CITY_ARRIVAL": "上海",
            "MODE": "77B"
        },
        "41202": {
            "AIRLINE_CODE": "MF1455",
            "FLIGHT_ID": 41202,
            "DEPARTURE_AIRPORT": "广州新白云国际机场",
            "ARRIVAL_AIRPORT": "上海虹桥国际机场",
            "TIME_DEPARTURE": "6:15:05",
            "TIME_ARRIVAL": "6:17:20",
            "CITY_DEPARTURE": "广州",
            "CITY_ARRIVAL": "上海",
            "MODE": "77B"
        },
        "41203": {
            "AIRLINE_CODE": "MF1455",
            "FLIGHT_ID": 41203,
            "DEPARTURE_AIRPORT": "广州新白云国际机场",
            "ARRIVAL_AIRPORT": "上海虹桥国际机场",
            "TIME_DEPARTURE": "7:15:05",
            "TIME_ARRIVAL": "7:17:20",
            "CITY_DEPARTURE": "广州",
            "CITY_ARRIVAL": "上海",
            "MODE": "77B"
        },
        "41674": {
            "AIRLINE_CODE": "CZ3109",
            "FLIGHT_ID": 41674,
            "DEPARTURE_AIRPORT": "广州新白云国际机场",
            "ARRIVAL_AIRPORT": "北京首都国际机场",
            "TIME_DEPARTURE": "1:14:00",
            "TIME_ARRIVAL": "1:17:10",
            "CITY_DEPARTURE": "广州",
            "CITY_ARRIVAL": "北京",
            "MODE": "77B"
        },
        "41675": {
            "AIRLINE_CODE": "CZ3109",
            "FLIGHT_ID": 41675,
            "DEPARTURE_AIRPORT": "广州新白云国际机场",
            "ARRIVAL_AIRPORT": "北京首都国际机场",
            "TIME_DEPARTURE": "2:14:00",
            "TIME_ARRIVAL": "2:17:10",
            "CITY_DEPARTURE": "广州",
            "CITY_ARRIVAL": "北京",
            "MODE": "77B"
        },
        "41676": {
            "AIRLINE_CODE": "CZ3109",
            "FLIGHT_ID": 41676,
            "DEPARTURE_AIRPORT": "广州新白云国际机场",
            "ARRIVAL_AIRPORT": "北京首都国际机场",
            "TIME_DEPARTURE": "3:14:00",
            "TIME_ARRIVAL": "3:17:10",
            "CITY_DEPARTURE": "广州",
            "CITY_ARRIVAL": "北京",
            "MODE": "77B"
        },
        "41677": {
            "AIRLINE_CODE": "CZ3109",
            "FLIGHT_ID": 41677,
            "DEPARTURE_AIRPORT": "广州新白云国际机场",
            "ARRIVAL_AIRPORT": "北京首都国际机场",
            "TIME_DEPARTURE": "4:14:00",
            "TIME_ARRIVAL": "4:17:10",
            "CITY_DEPARTURE": "广州",
            "CITY_ARRIVAL": "北京",
            "MODE": "77B"
        },
        "41678": {
            "AIRLINE_CODE": "CZ3109",
            "FLIGHT_ID": 41678,
            "DEPARTURE_AIRPORT": "广州新白云国际机场",
            "ARRIVAL_AIRPORT": "北京首都国际机场",
            "TIME_DEPARTURE": "5:14:00",
            "TIME_ARRIVAL": "5:17:10",
            "CITY_DEPARTURE": "广州",
            "CITY_ARRIVAL": "北京",
            "MODE": "77B"
        },
        "41679": {
            "AIRLINE_CODE": "CZ3109",
            "FLIGHT_ID": 41679,
            "DEPARTURE_AIRPORT": "广州新白云国际机场",
            "ARRIVAL_AIRPORT": "北京首都国际机场",
            "TIME_DEPARTURE": "6:14:00",
            "TIME_ARRIVAL": "6:17:10",
            "CITY_DEPARTURE": "广州",
            "CITY_ARRIVAL": "北京",
            "MODE": "77B"
        },
        "41680": {
            "AIRLINE_CODE": "CZ3109",
            "FLIGHT_ID": 41680,
            "DEPARTURE_AIRPORT": "广州新白云国际机场",
            "ARRIVAL_AIRPORT": "北京首都国际机场",
            "TIME_DEPARTURE": "7:14:00",
            "TIME_ARRIVAL": "7:17:10",
            "CITY_DEPARTURE": "广州",
            "CITY_ARRIVAL": "北京",
            "MODE": "77B"
        }
    },
    "edges": {
        "6859_41184": {
            "from": 6859,
            "to": 41184
        },
        "6859_41185": {
            "from": 6859,
            "to": 41185
        },
        "6859_41186": {
            "from": 6859,
            "to": 41186
        },
        "6859_41187": {
            "from": 6859,
            "to": 41187
        },
        "6859_41188": {
            "from": 6859,
            "to": 41188
        },
        "6859_41189": {
            "from": 6859,
            "to": 41189
        },
        "6859_41191": {
            "from": 6859,
            "to": 41191
        },
        "6859_41192": {
            "from": 6859,
            "to": 41192
        },
        "6859_41193": {
            "from": 6859,
            "to": 41193
        },
        "6859_41194": {
            "from": 6859,
            "to": 41194
        },
        "6859_41195": {
            "from": 6859,
            "to": 41195
        },
        "6859_41196": {
            "from": 6859,
            "to": 41196
        },
        "6859_41198": {
            "from": 6859,
            "to": 41198
        },
        "6859_41199": {
            "from": 6859,
            "to": 41199
        },
        "6859_41200": {
            "from": 6859,
            "to": 41200
        },
        "6859_41201": {
            "from": 6859,
            "to": 41201
        },
        "6859_41202": {
            "from": 6859,
            "to": 41202
        },
        "6859_41203": {
            "from": 6859,
            "to": 41203
        },
        "6859_41675": {
            "from": 6859,
            "to": 41675
        },
        "6859_41676": {
            "from": 6859,
            "to": 41676
        },
        "6859_41677": {
            "from": 6859,
            "to": 41677
        },
        "6859_41678": {
            "from": 6859,
            "to": 41678
        },
        "6859_41679": {
            "from": 6859,
            "to": 41679
        },
        "6859_41680": {
            "from": 6859,
            "to": 41680
        },
        "6860_41185": {
            "from": 6860,
            "to": 41185
        },
        "6860_41186": {
            "from": 6860,
            "to": 41186
        },
        "6860_41187": {
            "from": 6860,
            "to": 41187
        },
        "6860_41188": {
            "from": 6860,
            "to": 41188
        },
        "6860_41189": {
            "from": 6860,
            "to": 41189
        },
        "6860_41192": {
            "from": 6860,
            "to": 41192
        },
        "6860_41193": {
            "from": 6860,
            "to": 41193
        },
        "6860_41194": {
            "from": 6860,
            "to": 41194
        },
        "6860_41195": {
            "from": 6860,
            "to": 41195
        },
        "6860_41196": {
            "from": 6860,
            "to": 41196
        },
        "6860_41199": {
            "from": 6860,
            "to": 41199
        },
        "6860_41200": {
            "from": 6860,
            "to": 41200
        },
        "6860_41201": {
            "from": 6860,
            "to": 41201
        },
        "6860_41202": {
            "from": 6860,
            "to": 41202
        },
        "6860_41203": {
            "from": 6860,
            "to": 41203
        },
        "6860_41676": {
            "from": 6860,
            "to": 41676
        },
        "6860_41677": {
            "from": 6860,
            "to": 41677
        },
        "6860_41678": {
            "from": 6860,
            "to": 41678
        },
        "6860_41679": {
            "from": 6860,
            "to": 41679
        },
        "6860_41680": {
            "from": 6860,
            "to": 41680
        },
        "6861_41186": {
            "from": 6861,
            "to": 41186
        },
        "6861_41187": {
            "from": 6861,
            "to": 41187
        },
        "6861_41188": {
            "from": 6861,
            "to": 41188
        },
        "6861_41189": {
            "from": 6861,
            "to": 41189
        },
        "6861_41193": {
            "from": 6861,
            "to": 41193
        },
        "6861_41194": {
            "from": 6861,
            "to": 41194
        },
        "6861_41195": {
            "from": 6861,
            "to": 41195
        },
        "6861_41196": {
            "from": 6861,
            "to": 41196
        },
        "6861_41200": {
            "from": 6861,
            "to": 41200
        },
        "6861_41201": {
            "from": 6861,
            "to": 41201
        },
        "6861_41202": {
            "from": 6861,
            "to": 41202
        },
        "6861_41203": {
            "from": 6861,
            "to": 41203
        },
        "6861_41677": {
            "from": 6861,
            "to": 41677
        },
        "6861_41678": {
            "from": 6861,
            "to": 41678
        },
        "6861_41679": {
            "from": 6861,
            "to": 41679
        },
        "6861_41680": {
            "from": 6861,
            "to": 41680
        },
        "6862_41187": {
            "from": 6862,
            "to": 41187
        },
        "6862_41188": {
            "from": 6862,
            "to": 41188
        },
        "6862_41189": {
            "from": 6862,
            "to": 41189
        },
        "6862_41194": {
            "from": 6862,
            "to": 41194
        },
        "6862_41195": {
            "from": 6862,
            "to": 41195
        },
        "6862_41196": {
            "from": 6862,
            "to": 41196
        },
        "6862_41201": {
            "from": 6862,
            "to": 41201
        },
        "6862_41202": {
            "from": 6862,
            "to": 41202
        },
        "6862_41203": {
            "from": 6862,
            "to": 41203
        },
        "6862_41678": {
            "from": 6862,
            "to": 41678
        },
        "6862_41679": {
            "from": 6862,
            "to": 41679
        },
        "6862_41680": {
            "from": 6862,
            "to": 41680
        },
        "6863_41188": {
            "from": 6863,
            "to": 41188
        },
        "6863_41189": {
            "from": 6863,
            "to": 41189
        },
        "6863_41195": {
            "from": 6863,
            "to": 41195
        },
        "6863_41196": {
            "from": 6863,
            "to": 41196
        },
        "6863_41202": {
            "from": 6863,
            "to": 41202
        },
        "6863_41203": {
            "from": 6863,
            "to": 41203
        },
        "6863_41679": {
            "from": 6863,
            "to": 41679
        },
        "6863_41680": {
            "from": 6863,
            "to": 41680
        },
        "6864_41189": {
            "from": 6864,
            "to": 41189
        },
        "6864_41196": {
            "from": 6864,
            "to": 41196
        },
        "6864_41203": {
            "from": 6864,
            "to": 41203
        },
        "6864_41680": {
            "from": 6864,
            "to": 41680
        },
        "6866_41184": {
            "from": 6866,
            "to": 41184
        },
        "6866_41185": {
            "from": 6866,
            "to": 41185
        },
        "6866_41186": {
            "from": 6866,
            "to": 41186
        },
        "6866_41187": {
            "from": 6866,
            "to": 41187
        },
        "6866_41188": {
            "from": 6866,
            "to": 41188
        },
        "6866_41189": {
            "from": 6866,
            "to": 41189
        },
        "6866_41191": {
            "from": 6866,
            "to": 41191
        },
        "6866_41192": {
            "from": 6866,
            "to": 41192
        },
        "6866_41193": {
            "from": 6866,
            "to": 41193
        },
        "6866_41194": {
            "from": 6866,
            "to": 41194
        },
        "6866_41195": {
            "from": 6866,
            "to": 41195
        },
        "6866_41196": {
            "from": 6866,
            "to": 41196
        },
        "6866_41198": {
            "from": 6866,
            "to": 41198
        },
        "6866_41199": {
            "from": 6866,
            "to": 41199
        },
        "6866_41200": {
            "from": 6866,
            "to": 41200
        },
        "6866_41201": {
            "from": 6866,
            "to": 41201
        },
        "6866_41202": {
            "from": 6866,
            "to": 41202
        },
        "6866_41203": {
            "from": 6866,
            "to": 41203
        },
        "6866_41675": {
            "from": 6866,
            "to": 41675
        },
        "6866_41676": {
            "from": 6866,
            "to": 41676
        },
        "6866_41677": {
            "from": 6866,
            "to": 41677
        },
        "6866_41678": {
            "from": 6866,
            "to": 41678
        },
        "6866_41679": {
            "from": 6866,
            "to": 41679
        },
        "6866_41680": {
            "from": 6866,
            "to": 41680
        },
        "6867_41185": {
            "from": 6867,
            "to": 41185
        },
        "6867_41186": {
            "from": 6867,
            "to": 41186
        },
        "6867_41187": {
            "from": 6867,
            "to": 41187
        },
        "6867_41188": {
            "from": 6867,
            "to": 41188
        },
        "6867_41189": {
            "from": 6867,
            "to": 41189
        },
        "6867_41192": {
            "from": 6867,
            "to": 41192
        },
        "6867_41193": {
            "from": 6867,
            "to": 41193
        },
        "6867_41194": {
            "from": 6867,
            "to": 41194
        },
        "6867_41195": {
            "from": 6867,
            "to": 41195
        },
        "6867_41196": {
            "from": 6867,
            "to": 41196
        },
        "6867_41199": {
            "from": 6867,
            "to": 41199
        },
        "6867_41200": {
            "from": 6867,
            "to": 41200
        },
        "6867_41201": {
            "from": 6867,
            "to": 41201
        },
        "6867_41202": {
            "from": 6867,
            "to": 41202
        },
        "6867_41203": {
            "from": 6867,
            "to": 41203
        },
        "6867_41676": {
            "from": 6867,
            "to": 41676
        },
        "6867_41677": {
            "from": 6867,
            "to": 41677
        },
        "6867_41678": {
            "from": 6867,
            "to": 41678
        },
        "6867_41679": {
            "from": 6867,
            "to": 41679
        },
        "6867_41680": {
            "from": 6867,
            "to": 41680
        },
        "6868_41186": {
            "from": 6868,
            "to": 41186
        },
        "6868_41187": {
            "from": 6868,
            "to": 41187
        },
        "6868_41188": {
            "from": 6868,
            "to": 41188
        },
        "6868_41189": {
            "from": 6868,
            "to": 41189
        },
        "6868_41193": {
            "from": 6868,
            "to": 41193
        },
        "6868_41194": {
            "from": 6868,
            "to": 41194
        },
        "6868_41195": {
            "from": 6868,
            "to": 41195
        },
        "6868_41196": {
            "from": 6868,
            "to": 41196
        },
        "6868_41200": {
            "from": 6868,
            "to": 41200
        },
        "6868_41201": {
            "from": 6868,
            "to": 41201
        },
        "6868_41202": {
            "from": 6868,
            "to": 41202
        },
        "6868_41203": {
            "from": 6868,
            "to": 41203
        },
        "6868_41677": {
            "from": 6868,
            "to": 41677
        },
        "6868_41678": {
            "from": 6868,
            "to": 41678
        },
        "6868_41679": {
            "from": 6868,
            "to": 41679
        },
        "6868_41680": {
            "from": 6868,
            "to": 41680
        },
        "6869_41187": {
            "from": 6869,
            "to": 41187
        },
        "6869_41188": {
            "from": 6869,
            "to": 41188
        },
        "6869_41189": {
            "from": 6869,
            "to": 41189
        },
        "6869_41194": {
            "from": 6869,
            "to": 41194
        },
        "6869_41195": {
            "from": 6869,
            "to": 41195
        },
        "6869_41196": {
            "from": 6869,
            "to": 41196
        },
        "6869_41201": {
            "from": 6869,
            "to": 41201
        },
        "6869_41202": {
            "from": 6869,
            "to": 41202
        },
        "6869_41203": {
            "from": 6869,
            "to": 41203
        },
        "6869_41678": {
            "from": 6869,
            "to": 41678
        },
        "6869_41679": {
            "from": 6869,
            "to": 41679
        },
        "6869_41680": {
            "from": 6869,
            "to": 41680
        },
        "6870_41188": {
            "from": 6870,
            "to": 41188
        },
        "6870_41189": {
            "from": 6870,
            "to": 41189
        },
        "6870_41195": {
            "from": 6870,
            "to": 41195
        },
        "6870_41196": {
            "from": 6870,
            "to": 41196
        },
        "6870_41202": {
            "from": 6870,
            "to": 41202
        },
        "6870_41203": {
            "from": 6870,
            "to": 41203
        },
        "6870_41679": {
            "from": 6870,
            "to": 41679
        },
        "6870_41680": {
            "from": 6870,
            "to": 41680
        },
        "6871_41189": {
            "from": 6871,
            "to": 41189
        },
        "6871_41196": {
            "from": 6871,
            "to": 41196
        },
        "6871_41203": {
            "from": 6871,
            "to": 41203
        },
        "6871_41680": {
            "from": 6871,
            "to": 41680
        },
        "6873_41184": {
            "from": 6873,
            "to": 41184
        },
        "6873_41185": {
            "from": 6873,
            "to": 41185
        },
        "6873_41186": {
            "from": 6873,
            "to": 41186
        },
        "6873_41187": {
            "from": 6873,
            "to": 41187
        },
        "6873_41188": {
            "from": 6873,
            "to": 41188
        },
        "6873_41189": {
            "from": 6873,
            "to": 41189
        },
        "6873_41191": {
            "from": 6873,
            "to": 41191
        },
        "6873_41192": {
            "from": 6873,
            "to": 41192
        },
        "6873_41193": {
            "from": 6873,
            "to": 41193
        },
        "6873_41194": {
            "from": 6873,
            "to": 41194
        },
        "6873_41195": {
            "from": 6873,
            "to": 41195
        },
        "6873_41196": {
            "from": 6873,
            "to": 41196
        },
        "6873_41198": {
            "from": 6873,
            "to": 41198
        },
        "6873_41199": {
            "from": 6873,
            "to": 41199
        },
        "6873_41200": {
            "from": 6873,
            "to": 41200
        },
        "6873_41201": {
            "from": 6873,
            "to": 41201
        },
        "6873_41202": {
            "from": 6873,
            "to": 41202
        },
        "6873_41203": {
            "from": 6873,
            "to": 41203
        },
        "6873_41675": {
            "from": 6873,
            "to": 41675
        },
        "6873_41676": {
            "from": 6873,
            "to": 41676
        },
        "6873_41677": {
            "from": 6873,
            "to": 41677
        },
        "6873_41678": {
            "from": 6873,
            "to": 41678
        },
        "6873_41679": {
            "from": 6873,
            "to": 41679
        },
        "6873_41680": {
            "from": 6873,
            "to": 41680
        },
        "6874_41185": {
            "from": 6874,
            "to": 41185
        },
        "6874_41186": {
            "from": 6874,
            "to": 41186
        },
        "6874_41187": {
            "from": 6874,
            "to": 41187
        },
        "6874_41188": {
            "from": 6874,
            "to": 41188
        },
        "6874_41189": {
            "from": 6874,
            "to": 41189
        },
        "6874_41192": {
            "from": 6874,
            "to": 41192
        },
        "6874_41193": {
            "from": 6874,
            "to": 41193
        },
        "6874_41194": {
            "from": 6874,
            "to": 41194
        },
        "6874_41195": {
            "from": 6874,
            "to": 41195
        },
        "6874_41196": {
            "from": 6874,
            "to": 41196
        },
        "6874_41199": {
            "from": 6874,
            "to": 41199
        },
        "6874_41200": {
            "from": 6874,
            "to": 41200
        },
        "6874_41201": {
            "from": 6874,
            "to": 41201
        },
        "6874_41202": {
            "from": 6874,
            "to": 41202
        },
        "6874_41203": {
            "from": 6874,
            "to": 41203
        },
        "6874_41676": {
            "from": 6874,
            "to": 41676
        },
        "6874_41677": {
            "from": 6874,
            "to": 41677
        },
        "6874_41678": {
            "from": 6874,
            "to": 41678
        },
        "6874_41679": {
            "from": 6874,
            "to": 41679
        },
        "6874_41680": {
            "from": 6874,
            "to": 41680
        },
        "6875_41186": {
            "from": 6875,
            "to": 41186
        },
        "6875_41187": {
            "from": 6875,
            "to": 41187
        },
        "6875_41188": {
            "from": 6875,
            "to": 41188
        },
        "6875_41189": {
            "from": 6875,
            "to": 41189
        },
        "6875_41193": {
            "from": 6875,
            "to": 41193
        },
        "6875_41194": {
            "from": 6875,
            "to": 41194
        },
        "6875_41195": {
            "from": 6875,
            "to": 41195
        },
        "6875_41196": {
            "from": 6875,
            "to": 41196
        },
        "6875_41200": {
            "from": 6875,
            "to": 41200
        },
        "6875_41201": {
            "from": 6875,
            "to": 41201
        },
        "6875_41202": {
            "from": 6875,
            "to": 41202
        },
        "6875_41203": {
            "from": 6875,
            "to": 41203
        },
        "6875_41677": {
            "from": 6875,
            "to": 41677
        },
        "6875_41678": {
            "from": 6875,
            "to": 41678
        },
        "6875_41679": {
            "from": 6875,
            "to": 41679
        },
        "6875_41680": {
            "from": 6875,
            "to": 41680
        },
        "6876_41187": {
            "from": 6876,
            "to": 41187
        },
        "6876_41188": {
            "from": 6876,
            "to": 41188
        },
        "6876_41189": {
            "from": 6876,
            "to": 41189
        },
        "6876_41194": {
            "from": 6876,
            "to": 41194
        },
        "6876_41195": {
            "from": 6876,
            "to": 41195
        },
        "6876_41196": {
            "from": 6876,
            "to": 41196
        },
        "6876_41201": {
            "from": 6876,
            "to": 41201
        },
        "6876_41202": {
            "from": 6876,
            "to": 41202
        },
        "6876_41203": {
            "from": 6876,
            "to": 41203
        },
        "6876_41678": {
            "from": 6876,
            "to": 41678
        },
        "6876_41679": {
            "from": 6876,
            "to": 41679
        },
        "6876_41680": {
            "from": 6876,
            "to": 41680
        },
        "6877_41188": {
            "from": 6877,
            "to": 41188
        },
        "6877_41189": {
            "from": 6877,
            "to": 41189
        },
        "6877_41195": {
            "from": 6877,
            "to": 41195
        },
        "6877_41196": {
            "from": 6877,
            "to": 41196
        },
        "6877_41202": {
            "from": 6877,
            "to": 41202
        },
        "6877_41203": {
            "from": 6877,
            "to": 41203
        },
        "6877_41679": {
            "from": 6877,
            "to": 41679
        },
        "6877_41680": {
            "from": 6877,
            "to": 41680
        },
        "6878_41189": {
            "from": 6878,
            "to": 41189
        },
        "6878_41196": {
            "from": 6878,
            "to": 41196
        },
        "6878_41203": {
            "from": 6878,
            "to": 41203
        },
        "6878_41680": {
            "from": 6878,
            "to": 41680
        },
        "41183_6859": {
            "from": 41183,
            "to": 6859
        },
        "41183_6860": {
            "from": 41183,
            "to": 6860
        },
        "41183_6861": {
            "from": 41183,
            "to": 6861
        },
        "41183_6862": {
            "from": 41183,
            "to": 6862
        },
        "41183_6863": {
            "from": 41183,
            "to": 6863
        },
        "41183_6864": {
            "from": 41183,
            "to": 6864
        },
        "41183_6865": {
            "from": 41183,
            "to": 6865
        },
        "41183_6866": {
            "from": 41183,
            "to": 6866
        },
        "41183_6867": {
            "from": 41183,
            "to": 6867
        },
        "41183_6868": {
            "from": 41183,
            "to": 6868
        },
        "41183_6869": {
            "from": 41183,
            "to": 6869
        },
        "41183_6870": {
            "from": 41183,
            "to": 6870
        },
        "41183_6871": {
            "from": 41183,
            "to": 6871
        },
        "41183_6872": {
            "from": 41183,
            "to": 6872
        },
        "41183_6873": {
            "from": 41183,
            "to": 6873
        },
        "41183_6874": {
            "from": 41183,
            "to": 6874
        },
        "41183_6875": {
            "from": 41183,
            "to": 6875
        },
        "41183_6876": {
            "from": 41183,
            "to": 6876
        },
        "41183_6877": {
            "from": 41183,
            "to": 6877
        },
        "41183_6878": {
            "from": 41183,
            "to": 6878
        },
        "41183_6879": {
            "from": 41183,
            "to": 6879
        },
        "41184_6860": {
            "from": 41184,
            "to": 6860
        },
        "41184_6861": {
            "from": 41184,
            "to": 6861
        },
        "41184_6862": {
            "from": 41184,
            "to": 6862
        },
        "41184_6863": {
            "from": 41184,
            "to": 6863
        },
        "41184_6864": {
            "from": 41184,
            "to": 6864
        },
        "41184_6865": {
            "from": 41184,
            "to": 6865
        },
        "41184_6867": {
            "from": 41184,
            "to": 6867
        },
        "41184_6868": {
            "from": 41184,
            "to": 6868
        },
        "41184_6869": {
            "from": 41184,
            "to": 6869
        },
        "41184_6870": {
            "from": 41184,
            "to": 6870
        },
        "41184_6871": {
            "from": 41184,
            "to": 6871
        },
        "41184_6872": {
            "from": 41184,
            "to": 6872
        },
        "41184_6874": {
            "from": 41184,
            "to": 6874
        },
        "41184_6875": {
            "from": 41184,
            "to": 6875
        },
        "41184_6876": {
            "from": 41184,
            "to": 6876
        },
        "41184_6877": {
            "from": 41184,
            "to": 6877
        },
        "41184_6878": {
            "from": 41184,
            "to": 6878
        },
        "41184_6879": {
            "from": 41184,
            "to": 6879
        },
        "41185_6861": {
            "from": 41185,
            "to": 6861
        },
        "41185_6862": {
            "from": 41185,
            "to": 6862
        },
        "41185_6863": {
            "from": 41185,
            "to": 6863
        },
        "41185_6864": {
            "from": 41185,
            "to": 6864
        },
        "41185_6865": {
            "from": 41185,
            "to": 6865
        },
        "41185_6868": {
            "from": 41185,
            "to": 6868
        },
        "41185_6869": {
            "from": 41185,
            "to": 6869
        },
        "41185_6870": {
            "from": 41185,
            "to": 6870
        },
        "41185_6871": {
            "from": 41185,
            "to": 6871
        },
        "41185_6872": {
            "from": 41185,
            "to": 6872
        },
        "41185_6875": {
            "from": 41185,
            "to": 6875
        },
        "41185_6876": {
            "from": 41185,
            "to": 6876
        },
        "41185_6877": {
            "from": 41185,
            "to": 6877
        },
        "41185_6878": {
            "from": 41185,
            "to": 6878
        },
        "41185_6879": {
            "from": 41185,
            "to": 6879
        },
        "41186_6862": {
            "from": 41186,
            "to": 6862
        },
        "41186_6863": {
            "from": 41186,
            "to": 6863
        },
        "41186_6864": {
            "from": 41186,
            "to": 6864
        },
        "41186_6865": {
            "from": 41186,
            "to": 6865
        },
        "41186_6869": {
            "from": 41186,
            "to": 6869
        },
        "41186_6870": {
            "from": 41186,
            "to": 6870
        },
        "41186_6871": {
            "from": 41186,
            "to": 6871
        },
        "41186_6872": {
            "from": 41186,
            "to": 6872
        },
        "41186_6876": {
            "from": 41186,
            "to": 6876
        },
        "41186_6877": {
            "from": 41186,
            "to": 6877
        },
        "41186_6878": {
            "from": 41186,
            "to": 6878
        },
        "41186_6879": {
            "from": 41186,
            "to": 6879
        },
        "41187_6863": {
            "from": 41187,
            "to": 6863
        },
        "41187_6864": {
            "from": 41187,
            "to": 6864
        },
        "41187_6865": {
            "from": 41187,
            "to": 6865
        },
        "41187_6870": {
            "from": 41187,
            "to": 6870
        },
        "41187_6871": {
            "from": 41187,
            "to": 6871
        },
        "41187_6872": {
            "from": 41187,
            "to": 6872
        },
        "41187_6877": {
            "from": 41187,
            "to": 6877
        },
        "41187_6878": {
            "from": 41187,
            "to": 6878
        },
        "41187_6879": {
            "from": 41187,
            "to": 6879
        },
        "41188_6864": {
            "from": 41188,
            "to": 6864
        },
        "41188_6865": {
            "from": 41188,
            "to": 6865
        },
        "41188_6871": {
            "from": 41188,
            "to": 6871
        },
        "41188_6872": {
            "from": 41188,
            "to": 6872
        },
        "41188_6878": {
            "from": 41188,
            "to": 6878
        },
        "41188_6879": {
            "from": 41188,
            "to": 6879
        },
        "41189_6865": {
            "from": 41189,
            "to": 6865
        },
        "41189_6872": {
            "from": 41189,
            "to": 6872
        },
        "41189_6879": {
            "from": 41189,
            "to": 6879
        },
        "41190_6859": {
            "from": 41190,
            "to": 6859
        },
        "41190_6860": {
            "from": 41190,
            "to": 6860
        },
        "41190_6861": {
            "from": 41190,
            "to": 6861
        },
        "41190_6862": {
            "from": 41190,
            "to": 6862
        },
        "41190_6863": {
            "from": 41190,
            "to": 6863
        },
        "41190_6864": {
            "from": 41190,
            "to": 6864
        },
        "41190_6865": {
            "from": 41190,
            "to": 6865
        },
        "41190_6866": {
            "from": 41190,
            "to": 6866
        },
        "41190_6867": {
            "from": 41190,
            "to": 6867
        },
        "41190_6868": {
            "from": 41190,
            "to": 6868
        },
        "41190_6869": {
            "from": 41190,
            "to": 6869
        },
        "41190_6870": {
            "from": 41190,
            "to": 6870
        },
        "41190_6871": {
            "from": 41190,
            "to": 6871
        },
        "41190_6872": {
            "from": 41190,
            "to": 6872
        },
        "41190_6873": {
            "from": 41190,
            "to": 6873
        },
        "41190_6874": {
            "from": 41190,
            "to": 6874
        },
        "41190_6875": {
            "from": 41190,
            "to": 6875
        },
        "41190_6876": {
            "from": 41190,
            "to": 6876
        },
        "41190_6877": {
            "from": 41190,
            "to": 6877
        },
        "41190_6878": {
            "from": 41190,
            "to": 6878
        },
        "41190_6879": {
            "from": 41190,
            "to": 6879
        },
        "41191_6860": {
            "from": 41191,
            "to": 6860
        },
        "41191_6861": {
            "from": 41191,
            "to": 6861
        },
        "41191_6862": {
            "from": 41191,
            "to": 6862
        },
        "41191_6863": {
            "from": 41191,
            "to": 6863
        },
        "41191_6864": {
            "from": 41191,
            "to": 6864
        },
        "41191_6865": {
            "from": 41191,
            "to": 6865
        },
        "41191_6867": {
            "from": 41191,
            "to": 6867
        },
        "41191_6868": {
            "from": 41191,
            "to": 6868
        },
        "41191_6869": {
            "from": 41191,
            "to": 6869
        },
        "41191_6870": {
            "from": 41191,
            "to": 6870
        },
        "41191_6871": {
            "from": 41191,
            "to": 6871
        },
        "41191_6872": {
            "from": 41191,
            "to": 6872
        },
        "41191_6874": {
            "from": 41191,
            "to": 6874
        },
        "41191_6875": {
            "from": 41191,
            "to": 6875
        },
        "41191_6876": {
            "from": 41191,
            "to": 6876
        },
        "41191_6877": {
            "from": 41191,
            "to": 6877
        },
        "41191_6878": {
            "from": 41191,
            "to": 6878
        },
        "41191_6879": {
            "from": 41191,
            "to": 6879
        },
        "41192_6861": {
            "from": 41192,
            "to": 6861
        },
        "41192_6862": {
            "from": 41192,
            "to": 6862
        },
        "41192_6863": {
            "from": 41192,
            "to": 6863
        },
        "41192_6864": {
            "from": 41192,
            "to": 6864
        },
        "41192_6865": {
            "from": 41192,
            "to": 6865
        },
        "41192_6868": {
            "from": 41192,
            "to": 6868
        },
        "41192_6869": {
            "from": 41192,
            "to": 6869
        },
        "41192_6870": {
            "from": 41192,
            "to": 6870
        },
        "41192_6871": {
            "from": 41192,
            "to": 6871
        },
        "41192_6872": {
            "from": 41192,
            "to": 6872
        },
        "41192_6875": {
            "from": 41192,
            "to": 6875
        },
        "41192_6876": {
            "from": 41192,
            "to": 6876
        },
        "41192_6877": {
            "from": 41192,
            "to": 6877
        },
        "41192_6878": {
            "from": 41192,
            "to": 6878
        },
        "41192_6879": {
            "from": 41192,
            "to": 6879
        },
        "41193_6862": {
            "from": 41193,
            "to": 6862
        },
        "41193_6863": {
            "from": 41193,
            "to": 6863
        },
        "41193_6864": {
            "from": 41193,
            "to": 6864
        },
        "41193_6865": {
            "from": 41193,
            "to": 6865
        },
        "41193_6869": {
            "from": 41193,
            "to": 6869
        },
        "41193_6870": {
            "from": 41193,
            "to": 6870
        },
        "41193_6871": {
            "from": 41193,
            "to": 6871
        },
        "41193_6872": {
            "from": 41193,
            "to": 6872
        },
        "41193_6876": {
            "from": 41193,
            "to": 6876
        },
        "41193_6877": {
            "from": 41193,
            "to": 6877
        },
        "41193_6878": {
            "from": 41193,
            "to": 6878
        },
        "41193_6879": {
            "from": 41193,
            "to": 6879
        },
        "41194_6863": {
            "from": 41194,
            "to": 6863
        },
        "41194_6864": {
            "from": 41194,
            "to": 6864
        },
        "41194_6865": {
            "from": 41194,
            "to": 6865
        },
        "41194_6870": {
            "from": 41194,
            "to": 6870
        },
        "41194_6871": {
            "from": 41194,
            "to": 6871
        },
        "41194_6872": {
            "from": 41194,
            "to": 6872
        },
        "41194_6877": {
            "from": 41194,
            "to": 6877
        },
        "41194_6878": {
            "from": 41194,
            "to": 6878
        },
        "41194_6879": {
            "from": 41194,
            "to": 6879
        },
        "41195_6864": {
            "from": 41195,
            "to": 6864
        },
        "41195_6865": {
            "from": 41195,
            "to": 6865
        },
        "41195_6871": {
            "from": 41195,
            "to": 6871
        },
        "41195_6872": {
            "from": 41195,
            "to": 6872
        },
        "41195_6878": {
            "from": 41195,
            "to": 6878
        },
        "41195_6879": {
            "from": 41195,
            "to": 6879
        },
        "41196_6865": {
            "from": 41196,
            "to": 6865
        },
        "41196_6872": {
            "from": 41196,
            "to": 6872
        },
        "41196_6879": {
            "from": 41196,
            "to": 6879
        },
        "41197_6859": {
            "from": 41197,
            "to": 6859
        },
        "41197_6860": {
            "from": 41197,
            "to": 6860
        },
        "41197_6861": {
            "from": 41197,
            "to": 6861
        },
        "41197_6862": {
            "from": 41197,
            "to": 6862
        },
        "41197_6863": {
            "from": 41197,
            "to": 6863
        },
        "41197_6864": {
            "from": 41197,
            "to": 6864
        },
        "41197_6865": {
            "from": 41197,
            "to": 6865
        },
        "41197_6866": {
            "from": 41197,
            "to": 6866
        },
        "41197_6867": {
            "from": 41197,
            "to": 6867
        },
        "41197_6868": {
            "from": 41197,
            "to": 6868
        },
        "41197_6869": {
            "from": 41197,
            "to": 6869
        },
        "41197_6870": {
            "from": 41197,
            "to": 6870
        },
        "41197_6871": {
            "from": 41197,
            "to": 6871
        },
        "41197_6872": {
            "from": 41197,
            "to": 6872
        },
        "41197_6873": {
            "from": 41197,
            "to": 6873
        },
        "41197_6874": {
            "from": 41197,
            "to": 6874
        },
        "41197_6875": {
            "from": 41197,
            "to": 6875
        },
        "41197_6876": {
            "from": 41197,
            "to": 6876
        },
        "41197_6877": {
            "from": 41197,
            "to": 6877
        },
        "41197_6878": {
            "from": 41197,
            "to": 6878
        },
        "41197_6879": {
            "from": 41197,
            "to": 6879
        },
        "41198_6860": {
            "from": 41198,
            "to": 6860
        },
        "41198_6861": {
            "from": 41198,
            "to": 6861
        },
        "41198_6862": {
            "from": 41198,
            "to": 6862
        },
        "41198_6863": {
            "from": 41198,
            "to": 6863
        },
        "41198_6864": {
            "from": 41198,
            "to": 6864
        },
        "41198_6865": {
            "from": 41198,
            "to": 6865
        },
        "41198_6867": {
            "from": 41198,
            "to": 6867
        },
        "41198_6868": {
            "from": 41198,
            "to": 6868
        },
        "41198_6869": {
            "from": 41198,
            "to": 6869
        },
        "41198_6870": {
            "from": 41198,
            "to": 6870
        },
        "41198_6871": {
            "from": 41198,
            "to": 6871
        },
        "41198_6872": {
            "from": 41198,
            "to": 6872
        },
        "41198_6874": {
            "from": 41198,
            "to": 6874
        },
        "41198_6875": {
            "from": 41198,
            "to": 6875
        },
        "41198_6876": {
            "from": 41198,
            "to": 6876
        },
        "41198_6877": {
            "from": 41198,
            "to": 6877
        },
        "41198_6878": {
            "from": 41198,
            "to": 6878
        },
        "41198_6879": {
            "from": 41198,
            "to": 6879
        },
        "41199_6861": {
            "from": 41199,
            "to": 6861
        },
        "41199_6862": {
            "from": 41199,
            "to": 6862
        },
        "41199_6863": {
            "from": 41199,
            "to": 6863
        },
        "41199_6864": {
            "from": 41199,
            "to": 6864
        },
        "41199_6865": {
            "from": 41199,
            "to": 6865
        },
        "41199_6868": {
            "from": 41199,
            "to": 6868
        },
        "41199_6869": {
            "from": 41199,
            "to": 6869
        },
        "41199_6870": {
            "from": 41199,
            "to": 6870
        },
        "41199_6871": {
            "from": 41199,
            "to": 6871
        },
        "41199_6872": {
            "from": 41199,
            "to": 6872
        },
        "41199_6875": {
            "from": 41199,
            "to": 6875
        },
        "41199_6876": {
            "from": 41199,
            "to": 6876
        },
        "41199_6877": {
            "from": 41199,
            "to": 6877
        },
        "41199_6878": {
            "from": 41199,
            "to": 6878
        },
        "41199_6879": {
            "from": 41199,
            "to": 6879
        },
        "41200_6862": {
            "from": 41200,
            "to": 6862
        },
        "41200_6863": {
            "from": 41200,
            "to": 6863
        },
        "41200_6864": {
            "from": 41200,
            "to": 6864
        },
        "41200_6865": {
            "from": 41200,
            "to": 6865
        },
        "41200_6869": {
            "from": 41200,
            "to": 6869
        },
        "41200_6870": {
            "from": 41200,
            "to": 6870
        },
        "41200_6871": {
            "from": 41200,
            "to": 6871
        },
        "41200_6872": {
            "from": 41200,
            "to": 6872
        },
        "41200_6876": {
            "from": 41200,
            "to": 6876
        },
        "41200_6877": {
            "from": 41200,
            "to": 6877
        },
        "41200_6878": {
            "from": 41200,
            "to": 6878
        },
        "41200_6879": {
            "from": 41200,
            "to": 6879
        },
        "41201_6863": {
            "from": 41201,
            "to": 6863
        },
        "41201_6864": {
            "from": 41201,
            "to": 6864
        },
        "41201_6865": {
            "from": 41201,
            "to": 6865
        },
        "41201_6870": {
            "from": 41201,
            "to": 6870
        },
        "41201_6871": {
            "from": 41201,
            "to": 6871
        },
        "41201_6872": {
            "from": 41201,
            "to": 6872
        },
        "41201_6877": {
            "from": 41201,
            "to": 6877
        },
        "41201_6878": {
            "from": 41201,
            "to": 6878
        },
        "41201_6879": {
            "from": 41201,
            "to": 6879
        },
        "41202_6864": {
            "from": 41202,
            "to": 6864
        },
        "41202_6865": {
            "from": 41202,
            "to": 6865
        },
        "41202_6871": {
            "from": 41202,
            "to": 6871
        },
        "41202_6872": {
            "from": 41202,
            "to": 6872
        },
        "41202_6878": {
            "from": 41202,
            "to": 6878
        },
        "41202_6879": {
            "from": 41202,
            "to": 6879
        },
        "41203_6865": {
            "from": 41203,
            "to": 6865
        },
        "41203_6872": {
            "from": 41203,
            "to": 6872
        },
        "41203_6879": {
            "from": 41203,
            "to": 6879
        }
    }
}