{"20466":{"AIRLINE_CODE":"CA1313","FLIGHT_ID":20466,"DEPARTURE_AIRPORT":"\u5317\u4eac\u9996\u90fd\u56fd\u9645\u673a\u573a","ARRIVAL_AIRPORT":"\u6df1\u5733\u5b9d\u5b89\u56fd\u9645\u673a\u573a","TIME_DEPARTURE":"2:11:30","TIME_ARRIVAL":"2:14:40","CITY_DEPARTURE":"\u5317\u4eac","CITY_ARRIVAL":"\u6df1\u5733","MODE":"744"},"20467":{"AIRLINE_CODE":"CA1313","FLIGHT_ID":20467,"DEPARTURE_AIRPORT":"\u5317\u4eac\u9996\u90fd\u56fd\u9645\u673a\u573a","ARRIVAL_AIRPORT":"\u6df1\u5733\u5b9d\u5b89\u56fd\u9645\u673a\u573a","TIME_DEPARTURE":"5:11:30","TIME_ARRIVAL":"5:14:40","CITY_DEPARTURE":"\u5317\u4eac","CITY_ARRIVAL":"\u6df1\u5733","MODE":"744"},"20468":{"AIRLINE_CODE":"CA1313","FLIGHT_ID":20468,"DEPARTURE_AIRPORT":"\u5317\u4eac\u9996\u90fd\u56fd\u9645\u673a\u573a","ARRIVAL_AIRPORT":"\u6df1\u5733\u5b9d\u5b89\u56fd\u9645\u673a\u573a","TIME_DEPARTURE":"7:11:30","TIME_ARRIVAL":"7:14:40","CITY_DEPARTURE":"\u5317\u4eac","CITY_ARRIVAL":"\u6df1\u5733","MODE":"744"},"69563":{"AIRLINE_CODE":"ZH1314","FLIGHT_ID":69563,"DEPARTURE_AIRPORT":"\u6df1\u5733\u5b9d\u5b89\u56fd\u9645\u673a\u573a","ARRIVAL_AIRPORT":"\u5317\u4eac\u9996\u90fd\u56fd\u9645\u673a\u573a","TIME_DEPARTURE":"2:16:00","TIME_ARRIVAL":"2:19:05","CITY_DEPARTURE":"\u6df1\u5733","CITY_ARRIVAL":"\u5317\u4eac","MODE":"744"},"69564":{"AIRLINE_CODE":"ZH1314","FLIGHT_ID":69564,"DEPARTURE_AIRPORT":"\u6df1\u5733\u5b9d\u5b89\u56fd\u9645\u673a\u573a","ARRIVAL_AIRPORT":"\u5317\u4eac\u9996\u90fd\u56fd\u9645\u673a\u573a","TIME_DEPARTURE":"5:16:00","TIME_ARRIVAL":"5:19:05","CITY_DEPARTURE":"\u6df1\u5733","CITY_ARRIVAL":"\u5317\u4eac","MODE":"744"},"69565":{"AIRLINE_CODE":"ZH1314","FLIGHT_ID":69565,"DEPARTURE_AIRPORT":"\u6df1\u5733\u5b9d\u5b89\u56fd\u9645\u673a\u573a","ARRIVAL_AIRPORT":"\u5317\u4eac\u9996\u90fd\u56fd\u9645\u673a\u573a","TIME_DEPARTURE":"7:16:00","TIME_ARRIVAL":"7:19:05","CITY_DEPARTURE":"\u6df1\u5733","CITY_ARRIVAL":"\u5317\u4eac","MODE":"744"},"69566":{"AIRLINE_CODE":"CA1314","FLIGHT_ID":69566,"DEPARTURE_AIRPORT":"\u6df1\u5733\u5b9d\u5b89\u56fd\u9645\u673a\u573a","ARRIVAL_AIRPORT":"\u5317\u4eac\u9996\u90fd\u56fd\u9645\u673a\u573a","TIME_DEPARTURE":"2:16:00","TIME_ARRIVAL":"2:19:05","CITY_DEPARTURE":"\u6df1\u5733","CITY_ARRIVAL":"\u5317\u4eac","MODE":"744"},"69567":{"AIRLINE_CODE":"CA1314","FLIGHT_ID":69567,"DEPARTURE_AIRPORT":"\u6df1\u5733\u5b9d\u5b89\u56fd\u9645\u673a\u573a","ARRIVAL_AIRPORT":"\u5317\u4eac\u9996\u90fd\u56fd\u9645\u673a\u573a","TIME_DEPARTURE":"5:16:00","TIME_ARRIVAL":"5:19:05","CITY_DEPARTURE":"\u6df1\u5733","CITY_ARRIVAL":"\u5317\u4eac","MODE":"744"},"69568":{"AIRLINE_CODE":"CA1314","FLIGHT_ID":69568,"DEPARTURE_AIRPORT":"\u6df1\u5733\u5b9d\u5b89\u56fd\u9645\u673a\u573a","ARRIVAL_AIRPORT":"\u5317\u4eac\u9996\u90fd\u56fd\u9645\u673a\u573a","TIME_DEPARTURE":"7:16:00","TIME_ARRIVAL":"7:19:05","CITY_DEPARTURE":"\u6df1\u5733","CITY_ARRIVAL":"\u5317\u4eac","MODE":"744"}}